query_filter/__init__.py
query_filter/filter.py
query_filter/query.py
query_filter-1.0.3.dist-info/LICENSE
query_filter-1.0.3.dist-info/METADATA
query_filter-1.0.3.dist-info/WHEEL
query_filter-1.0.3.dist-info/top_level.txt
query_filter-1.0.3.dist-info/RECORD
