Metadata-Version: 2.1
Name: query-filter
Version: 1.0.3
Summary: Python's filter function with composable queries.
Home-page: https://github.com/simoncrowe/python-query-filter
Author: Simon Crowe
Author-email: simon.r.crowe@pm.me
Classifier: Programming Language :: Python :: 3
Classifier: License :: OSI Approved :: MIT License
Classifier: Operating System :: OS Independent
Requires-Python: >=3.6
License-File: LICENSE
